mlops_utilities/__init__.py
mlops_utilities/actions.py
mlops_utilities/helpers.py
mlops_utilities-0.4.4.dist-info/WHEEL
mlops_utilities-0.4.4.dist-info/METADATA
mlops_utilities-0.4.4.dist-info/RECORD
