Metadata-Version: 2.1
Name: mlops-utilities
Version: 0.4.4
Summary: 
Author: Provectus Team
Author-email: mlops@provectus.com
Requires-Python: >=3.8
Classifier: Operating System :: OS Independent
Classifier: Programming Language :: Python :: 3
Classifier: Programming Language :: Python :: 3.8
Classifier: Programming Language :: Python :: 3.9
Classifier: Programming Language :: Python :: 3.10
Classifier: Programming Language :: Python :: 3.11
Requires-Dist: boto3 (>=1.26,<1.27)
Requires-Dist: omegaconf (>=2.2,<2.3)
Requires-Dist: pytest (==7.2.0)
Requires-Dist: sagemaker (>=2.129,<2.130)
